dit_cli/__init__.py
dit_cli/__main__.py
dit_cli/built_in.py
dit_cli/cli.py
dit_cli/color.py
dit_cli/exceptions.py
dit_cli/grammar.py
dit_cli/interpret_context.py
dit_cli/interpreter.py
dit_cli/lang_daemon.py
dit_cli/oop.py
dit_cli/preprocessor.py
dit_cli/settings.py
dit_cli-0.5.1.dist-info/entry_points.txt
dit_cli-0.5.1.dist-info/LICENSE
dit_cli-0.5.1.dist-info/WHEEL
dit_cli-0.5.1.dist-info/METADATA
dit_cli-0.5.1.dist-info/RECORD
