Metadata-Version: 2.1
Name: dit-cli
Version: 0.5.1
Summary: The CLI for dit
Home-page: https://www.ditabase.io/
License: GPL-3.0-or-later
Author: Isaiah Shiner
Author-email: shiner.isaiah@gmail.com
Requires-Python: >=3.8,<4.0
Classifier: License :: OSI Approved :: GNU General Public License v3 or later (GPLv3+)
Classifier: Operating System :: OS Independent
Classifier: Programming Language :: Python :: 3
Classifier: Programming Language :: Python :: 3.8
Classifier: Programming Language :: Python :: 3.9
